happtiq_commons_gen_ai/__init__.py
happtiq_commons_gen_ai/chatgpt_api_service.py
happtiq_commons_gen_ai/gemini_service.py
happtiq_commons_gen_ai-2.0.1.dist-info/METADATA
happtiq_commons_gen_ai-2.0.1.dist-info/WHEEL
happtiq_commons_gen_ai-2.0.1.dist-info/top_level.txt
happtiq_commons_gen_ai-2.0.1.dist-info/RECORD
