Metadata-Version: 2.4
Name: happtiq_commons_gen_ai
Version: 2.0.1
Requires-Python: >=3.9
Requires-Dist: google-cloud-aiplatform
Requires-Dist: openai
Provides-Extra: dev
Requires-Dist: pytest; extra == "dev"
Requires-Dist: pytest-mock; extra == "dev"
